{
  "project_info": {
    "project_number": "795053025552",
    "project_id": "gopizza-d8345",
    "storage_bucket": "gopizza-d8345.appspot.com"
  },
  "client": [
    {
      "client_info": {
        "mobilesdk_app_id": "1:795053025552:android:889f8a8aa6c44d0b75dd95",
        "android_client_info": {
          "package_name": "com.gopizza"
        }
      },
      "oauth_client": [
        {
          "client_id": "795053025552-dkmk98cd46u1v302ljb3970dv07aa9eo.apps.googleusercontent.com",
          "client_type": 3
        }
      ],
      "api_key": [
        {
          "current_key": "AIzaSyApx-k_fhgua57h-oCCOzA_PmMnRvVHhKQ"
        }
      ],
      "services": {
        "appinvite_service": {
          "other_platform_oauth_client": [
            {
              "client_id": "795053025552-dkmk98cd46u1v302ljb3970dv07aa9eo.apps.googleusercontent.com",
              "client_type": 3
            }
          ]
        }
      }
    }
  ],
  "configuration_version": "1"
}